{"abilities":[{"ability":{"name":"stance-change"},"is_hidden":false}],"base_experience":234,"height":17,"held_items":[],"moves":[{"move":{"name":"swords-dance"},"version_group_details":[{"move_learn_method":{"name":"machine"}}]},{"move":{"name":"cut"},"version_group_details":[{"move_learn_method":{"name":"machine"}}]},{"move":{"name":"hyper-beam"},"version_group_details":[{"move_learn_method":{"name":"machine"}}]},{"move":{"name":"toxic"},"version_group_details":[{"move_learn_method":{"name":"machine"}}]},{"move":{"name":"double-team"},"version_group_details":[{"move_learn_method":{"name":"machine"}}]},{"move":{"name":"reflect"},"version_group_details":[{"move_learn_method":{"name":"machine"}}]},{"move":{"name":"rest"},"version_group_details":[{"move_learn_method":{"name":"machine"}}]},{"move":{"name":"rock-slide"},"version_group_details":[{"move_learn_method":{"name":"machine"}}]},{"move":{"name":"slash"},"version_group_details":[{"level_learned_at":1,"move_learn_method":{"name":"level-up"}}]},{"move":{"name":"substitute"},"version_group_details":[{"move_learn_method":{"name":"machine"}}]},{"move":{"name":"snore"},"version_group_details":[{"level_learned_at":0,"move_learn_method":{"name":"level-up"}}]},{"move":{"name":"spite"},"version_group_details":[{"level_learned_at":0,"move_learn_method":{"name":"level-up"}}]},{"move":{"name":"protect"},"version_group_details":[{"move_learn_method":{"name":"machine"}}]},{"move":{"name":"false-swipe"},"version_group_details":[{"move_learn_method":{"name":"machine"}}]},{"move":{"name":"swagger"},"version_group_details":[{"move_learn_method":{"name":"machine"}}]},{"move":{"name":"fury-cutter"},"version_group_details":[{"level_learned_at":1,"move_learn_method":{"name":"level-up"}}]},{"move":{"name":"attract"},"version_group_details":[{"move_learn_method":{"name":"machine"}}]},{"move":{"name":"sleep-talk"},"version_group_details":[{"move_learn_method":{"name":"machine"}}]},{"move":{"name":"return"},"version_group_details":[{"move_learn_method":{"name":"machine"}}]},{"move":{"name":"frustration"},"version_group_details":[{"move_learn_method":{"name":"machine"}}]},{"move":{"name":"pursuit"},"version_group_details":[{"level_learned_at":1,"move_learn_method":{"name":"level-up"}}]},{"move":{"name":"hidden-power"},"version_group_details":[{"move_learn_method":{"name":"machine"}}]},{"move":{"name":"rain-dance"},"version_group_details":[{"move_learn_method":{"name":"machine"}}]},{"move":{"name":"sunny-day"},"version_group_details":[{"move_learn_method":{"name":"machine"}}]},{"move":{"name":"shadow-ball"},"version_group_details":[{"move_learn_method":{"name":"machine"}}]},{"move":{"name":"rock-smash"},"version_group_details":[{"move_learn_method":{"name":"machine"}}]},{"move":{"name":"facade"},"version_group_details":[{"move_learn_method":{"name":"machine"}}]},{"move":{"name":"brick-break"},"version_group_details":[{"move_learn_method":{"name":"machine"}}]},{"move":{"name":"secret-power"},"version_group_details":[{"move_learn_method":{"name":"machine"}}]},{"move":{"name":"aerial-ace"},"version_group_details":[{"move_learn_method":{"name":"machine"}}]},{"move":{"name":"iron-defense"},"version_group_details":[{"level_learned_at":1,"move_learn_method":{"name":"level-up"}}]},{"move":{"name":"block"},"version_group_details":[{"level_learned_at":0,"move_learn_method":{"name":"level-up"}}]},{"move":{"name":"shock-wave"},"version_group_details":[{"level_learned_at":0,"move_learn_method":{"name":"level-up"}}]},{"move":{"name":"gyro-ball"},"version_group_details":[{"move_learn_method":{"name":"machine"}}]},{"move":{"name":"power-trick"},"version_group_details":[{"level_learned_at":1,"move_learn_method":{"name":"level-up"}}]},{"move":{"name":"magnet-rise"},"version_group_details":[{"level_learned_at":0,"move_learn_method":{"name":"level-up"}}]},{"move":{"name":"night-slash"},"version_group_details":[{"level_learned_at":1,"move_learn_method":{"name":"level-up"}}]},{"move":{"name":"giga-impact"},"version_group_details":[{"move_learn_method":{"name":"machine"}}]},{"move":{"name":"shadow-claw"},"version_group_details":[{"move_learn_method":{"name":"machine"}}]},{"move":{"name":"shadow-sneak"},"version_group_details":[{"level_learned_at":1,"move_learn_method":{"name":"level-up"}}]},{"move":{"name":"flash-cannon"},"version_group_details":[{"move_learn_method":{"name":"machine"}}]},{"move":{"name":"iron-head"},"version_group_details":[{"level_learned_at":1,"move_learn_method":{"name":"level-up"}}]},{"move":{"name":"head-smash"},"version_group_details":[{"level_learned_at":1,"move_learn_method":{"name":"level-up"}}]},{"move":{"name":"autotomize"},"version_group_details":[{"level_learned_at":1,"move_learn_method":{"name":"level-up"}}]},{"move":{"name":"after-you"},"version_group_details":[{"level_learned_at":0,"move_learn_method":{"name":"level-up"}}]},{"move":{"name":"round"},"version_group_details":[{"move_learn_method":{"name":"machine"}}]},{"move":{"name":"retaliate"},"version_group_details":[{"move_learn_method":{"name":"machine"}}]},{"move":{"name":"sacred-sword"},"version_group_details":[{"level_learned_at":1,"move_learn_method":{"name":"level-up"}}]},{"move":{"name":"kings-shield"},"version_group_details":[{"level_learned_at":1,"move_learn_method":{"name":"level-up"}}]},{"move":{"name":"confide"},"version_group_details":[{"move_learn_method":{"name":"machine"}}]},{"move":{"name":"brutal-swing"},"version_group_details":[{"move_learn_method":{"name":"machine"}}]}],"name":"aegislash-shield","species":{"base_happiness":70,"capture_rate":45,"egg_groups":[{"name":"mineral"}],"flavor_text_entries":[{"flavor_text":"Generations of kings were attended by these\nPokémon, which used their spectral power to\nmanipulate and control people and Pokémon.","language":{"name":"en"}}],"gender_rate":4,"genera":[{"genus":"Royal Sword Pokémon","language":{"name":"en"}}],"growth_rate":{"name":"Medium"},"hatch_counter":20,"id":681},"stats":[{"base_stat":60},{"base_stat":50},{"base_stat":150},{"base_stat":50},{"base_stat":150},{"base_stat":60}],"types":[{"slot":1,"type":{"name":"steel"}},{"slot":2,"type":{"name":"ghost"}}],"weight":530}
