{"abilities":[{"ability":{"name":"battle-armor"},"is_hidden":false},{"ability":{"name":"swift-swim"},"is_hidden":true}],"base_experience":71,"height":7,"held_items":[],"moves":[{"move":{"name":"scratch"},"version_group_details":[{"level_learned_at":1,"move_learn_method":{"name":"level-up"}}]},{"move":{"name":"swords-dance"},"version_group_details":[{"move_learn_method":{"name":"machine"}}]},{"move":{"name":"cut"},"version_group_details":[{"move_learn_method":{"name":"machine"}}]},{"move":{"name":"sand-attack"},"version_group_details":[{"move_learn_method":{"name":"egg"}}]},{"move":{"name":"headbutt"},"version_group_details":[{"level_learned_at":0,"move_learn_method":{"name":"level-up"}}]},{"move":{"name":"body-slam"},"version_group_details":[{"level_learned_at":0,"move_learn_method":{"name":"level-up"}}]},{"move":{"name":"double-edge"},"version_group_details":[{"level_learned_at":0,"move_learn_method":{"name":"level-up"}}]},{"move":{"name":"water-gun"},"version_group_details":[{"level_learned_at":7,"move_learn_method":{"name":"level-up"}}]},{"move":{"name":"string-shot"},"version_group_details":[{"level_learned_at":0,"move_learn_method":{"name":"level-up"}}]},{"move":{"name":"dig"},"version_group_details":[{"move_learn_method":{"name":"machine"}}]},{"move":{"name":"toxic"},"version_group_details":[{"move_learn_method":{"name":"machine"}}]},{"move":{"name":"mimic"},"version_group_details":[{"level_learned_at":0,"move_learn_method":{"name":"level-up"}}]},{"move":{"name":"screech"},"version_group_details":[{"move_learn_method":{"name":"egg"}}]},{"move":{"name":"double-team"},"version_group_details":[{"move_learn_method":{"name":"machine"}}]},{"move":{"name":"harden"},"version_group_details":[{"level_learned_at":1,"move_learn_method":{"name":"level-up"}}]},{"move":{"name":"rest"},"version_group_details":[{"move_learn_method":{"name":"machine"}}]},{"move":{"name":"rock-slide"},"version_group_details":[{"move_learn_method":{"name":"machine"}}]},{"move":{"name":"slash"},"version_group_details":[{"level_learned_at":34,"move_learn_method":{"name":"level-up"}}]},{"move":{"name":"substitute"},"version_group_details":[{"move_learn_method":{"name":"machine"}}]},{"move":{"name":"snore"},"version_group_details":[{"level_learned_at":0,"move_learn_method":{"name":"level-up"}}]},{"move":{"name":"curse"},"version_group_details":[{"move_learn_method":{"name":"egg"}}]},{"move":{"name":"protect"},"version_group_details":[{"move_learn_method":{"name":"machine"}}]},{"move":{"name":"mud-slap"},"version_group_details":[{"level_learned_at":0,"move_learn_method":{"name":"level-up"}}]},{"move":{"name":"sandstorm"},"version_group_details":[{"move_learn_method":{"name":"machine"}}]},{"move":{"name":"endure"},"version_group_details":[{"move_learn_method":{"name":"machine"}}]},{"move":{"name":"false-swipe"},"version_group_details":[{"move_learn_method":{"name":"machine"}}]},{"move":{"name":"swagger"},"version_group_details":[{"move_learn_method":{"name":"machine"}}]},{"move":{"name":"fury-cutter"},"version_group_details":[{"level_learned_at":10,"move_learn_method":{"name":"level-up"}}]},{"move":{"name":"attract"},"version_group_details":[{"move_learn_method":{"name":"machine"}}]},{"move":{"name":"sleep-talk"},"version_group_details":[{"move_learn_method":{"name":"machine"}}]},{"move":{"name":"return"},"version_group_details":[{"move_learn_method":{"name":"machine"}}]},{"move":{"name":"frustration"},"version_group_details":[{"move_learn_method":{"name":"machine"}}]},{"move":{"name":"rapid-spin"},"version_group_details":[{"move_learn_method":{"name":"egg"}}]},{"move":{"name":"metal-claw"},"version_group_details":[{"level_learned_at":17,"move_learn_method":{"name":"level-up"}}]},{"move":{"name":"hidden-power"},"version_group_details":[{"move_learn_method":{"name":"machine"}}]},{"move":{"name":"sunny-day"},"version_group_details":[{"move_learn_method":{"name":"machine"}}]},{"move":{"name":"ancient-power"},"version_group_details":[{"level_learned_at":21,"move_learn_method":{"name":"level-up"}}]},{"move":{"name":"rock-smash"},"version_group_details":[{"move_learn_method":{"name":"machine"}}]},{"move":{"name":"facade"},"version_group_details":[{"move_learn_method":{"name":"machine"}}]},{"move":{"name":"brick-break"},"version_group_details":[{"move_learn_method":{"name":"machine"}}]},{"move":{"name":"knock-off"},"version_group_details":[{"move_learn_method":{"name":"egg"}}]},{"move":{"name":"secret-power"},"version_group_details":[{"move_learn_method":{"name":"machine"}}]},{"move":{"name":"mud-sport"},"version_group_details":[{"level_learned_at":4,"move_learn_method":{"name":"level-up"}}]},{"move":{"name":"crush-claw"},"version_group_details":[{"level_learned_at":39,"move_learn_method":{"name":"level-up"}}]},{"move":{"name":"rock-tomb"},"version_group_details":[{"move_learn_method":{"name":"machine"}}]},{"move":{"name":"aerial-ace"},"version_group_details":[{"move_learn_method":{"name":"machine"}}]},{"move":{"name":"iron-defense"},"version_group_details":[{"move_learn_method":{"name":"egg"}}]},{"move":{"name":"rock-blast"},"version_group_details":[{"level_learned_at":55,"move_learn_method":{"name":"level-up"}}]},{"move":{"name":"water-pulse"},"version_group_details":[{"move_learn_method":{"name":"egg"}}]},{"move":{"name":"brine"},"version_group_details":[{"level_learned_at":29,"move_learn_method":{"name":"level-up"}}]},{"move":{"name":"natural-gift"},"version_group_details":[{"move_learn_method":{"name":"machine"}}]},{"move":{"name":"rock-polish"},"version_group_details":[{"move_learn_method":{"name":"machine"}}]},{"move":{"name":"x-scissor"},"version_group_details":[{"move_learn_method":{"name":"machine"}}]},{"move":{"name":"earth-power"},"version_group_details":[{"level_learned_at":0,"move_learn_method":{"name":"level-up"}}]},{"move":{"name":"cross-poison"},"version_group_details":[{"move_learn_method":{"name":"egg"}}]},{"move":{"name":"captivate"},"version_group_details":[{"move_learn_method":{"name":"machine"}}]},{"move":{"name":"stealth-rock"},"version_group_details":[{"level_learned_at":0,"move_learn_method":{"name":"level-up"}}]},{"move":{"name":"bug-bite"},"version_group_details":[{"level_learned_at":25,"move_learn_method":{"name":"level-up"}}]},{"move":{"name":"aqua-jet"},"version_group_details":[{"move_learn_method":{"name":"egg"}}]},{"move":{"name":"hone-claws"},"version_group_details":[{"move_learn_method":{"name":"machine"}}]},{"move":{"name":"smack-down"},"version_group_details":[{"move_learn_method":{"name":"machine"}}]},{"move":{"name":"round"},"version_group_details":[{"move_learn_method":{"name":"machine"}}]},{"move":{"name":"struggle-bug"},"version_group_details":[{"move_learn_method":{"name":"machine"}}]},{"move":{"name":"confide"},"version_group_details":[{"move_learn_method":{"name":"machine"}}]}],"name":"anorith","species":{"base_happiness":70,"capture_rate":45,"egg_groups":[{"name":"water3"}],"flavor_text_entries":[{"flavor_text":"ANORITH was regenerated from a\nprehistoric fossil. This primitive\nPOKéMON once lived in warm seas.\fIt grips its prey firmly between its\ntwo large claws.","language":{"name":"en"}}],"gender_rate":1,"genera":[{"genus":"Old Shrimp Pokémon","language":{"name":"en"}}],"growth_rate":{"name":"Slow-Then-Very-Fast"},"hatch_counter":30,"id":347},"stats":[{"base_stat":45},{"base_stat":95},{"base_stat":50},{"base_stat":40},{"base_stat":50},{"base_stat":75}],"types":[{"slot":1,"type":{"name":"rock"}},{"slot":2,"type":{"name":"bug"}}],"weight":125}
