{"abilities":[{"ability":{"name":"swarm"},"is_hidden":false},{"ability":{"name":"technician"},"is_hidden":true}],"base_experience":134,"height":10,"held_items":[{"item":{"name":"metronome"},"version_details":[{"rarity":5}]}],"moves":[{"move":{"name":"swords-dance"},"version_group_details":[{"move_learn_method":{"name":"machine"}}]},{"move":{"name":"cut"},"version_group_details":[{"move_learn_method":{"name":"machine"}}]},{"move":{"name":"growl"},"version_group_details":[{"level_learned_at":1,"move_learn_method":{"name":"level-up"}}]},{"move":{"name":"sing"},"version_group_details":[{"level_learned_at":18,"move_learn_method":{"name":"level-up"}}]},{"move":{"name":"hyper-beam"},"version_group_details":[{"move_learn_method":{"name":"machine"}}]},{"move":{"name":"strength"},"version_group_details":[{"move_learn_method":{"name":"machine"}}]},{"move":{"name":"absorb"},"version_group_details":[{"level_learned_at":14,"move_learn_method":{"name":"level-up"}}]},{"move":{"name":"string-shot"},"version_group_details":[{"level_learned_at":0,"move_learn_method":{"name":"level-up"}}]},{"move":{"name":"toxic"},"version_group_details":[{"move_learn_method":{"name":"machine"}}]},{"move":{"name":"screech"},"version_group_details":[{"level_learned_at":34,"move_learn_method":{"name":"level-up"}}]},{"move":{"name":"double-team"},"version_group_details":[{"move_learn_method":{"name":"machine"}}]},{"move":{"name":"focus-energy"},"version_group_details":[{"level_learned_at":22,"move_learn_method":{"name":"level-up"}}]},{"move":{"name":"bide"},"version_group_details":[{"level_learned_at":1,"move_learn_method":{"name":"level-up"}}]},{"move":{"name":"leech-life"},"version_group_details":[{"move_learn_method":{"name":"machine"}}]},{"move":{"name":"flash"},"version_group_details":[{"move_learn_method":{"name":"machine"}}]},{"move":{"name":"rest"},"version_group_details":[{"move_learn_method":{"name":"machine"}}]},{"move":{"name":"slash"},"version_group_details":[{"level_learned_at":26,"move_learn_method":{"name":"level-up"}}]},{"move":{"name":"substitute"},"version_group_details":[{"move_learn_method":{"name":"machine"}}]},{"move":{"name":"snore"},"version_group_details":[{"level_learned_at":0,"move_learn_method":{"name":"level-up"}}]},{"move":{"name":"protect"},"version_group_details":[{"move_learn_method":{"name":"machine"}}]},{"move":{"name":"mud-slap"},"version_group_details":[{"level_learned_at":0,"move_learn_method":{"name":"level-up"}}]},{"move":{"name":"perish-song"},"version_group_details":[{"level_learned_at":50,"move_learn_method":{"name":"level-up"}}]},{"move":{"name":"endure"},"version_group_details":[{"move_learn_method":{"name":"machine"}}]},{"move":{"name":"false-swipe"},"version_group_details":[{"move_learn_method":{"name":"machine"}}]},{"move":{"name":"swagger"},"version_group_details":[{"move_learn_method":{"name":"machine"}}]},{"move":{"name":"fury-cutter"},"version_group_details":[{"level_learned_at":1,"move_learn_method":{"name":"level-up"}}]},{"move":{"name":"attract"},"version_group_details":[{"move_learn_method":{"name":"machine"}}]},{"move":{"name":"sleep-talk"},"version_group_details":[{"move_learn_method":{"name":"machine"}}]},{"move":{"name":"heal-bell"},"version_group_details":[{"level_learned_at":0,"move_learn_method":{"name":"level-up"}}]},{"move":{"name":"return"},"version_group_details":[{"move_learn_method":{"name":"machine"}}]},{"move":{"name":"frustration"},"version_group_details":[{"move_learn_method":{"name":"machine"}}]},{"move":{"name":"hidden-power"},"version_group_details":[{"move_learn_method":{"name":"machine"}}]},{"move":{"name":"rain-dance"},"version_group_details":[{"move_learn_method":{"name":"machine"}}]},{"move":{"name":"sunny-day"},"version_group_details":[{"move_learn_method":{"name":"machine"}}]},{"move":{"name":"rock-smash"},"version_group_details":[{"move_learn_method":{"name":"machine"}}]},{"move":{"name":"uproar"},"version_group_details":[{"level_learned_at":0,"move_learn_method":{"name":"level-up"}}]},{"move":{"name":"facade"},"version_group_details":[{"move_learn_method":{"name":"machine"}}]},{"move":{"name":"taunt"},"version_group_details":[{"move_learn_method":{"name":"machine"}}]},{"move":{"name":"brick-break"},"version_group_details":[{"move_learn_method":{"name":"machine"}}]},{"move":{"name":"knock-off"},"version_group_details":[{"level_learned_at":0,"move_learn_method":{"name":"level-up"}}]},{"move":{"name":"endeavor"},"version_group_details":[{"level_learned_at":0,"move_learn_method":{"name":"level-up"}}]},{"move":{"name":"secret-power"},"version_group_details":[{"move_learn_method":{"name":"machine"}}]},{"move":{"name":"hyper-voice"},"version_group_details":[{"level_learned_at":0,"move_learn_method":{"name":"level-up"}}]},{"move":{"name":"silver-wind"},"version_group_details":[{"move_learn_method":{"name":"machine"}}]},{"move":{"name":"aerial-ace"},"version_group_details":[{"move_learn_method":{"name":"machine"}}]},{"move":{"name":"natural-gift"},"version_group_details":[{"move_learn_method":{"name":"machine"}}]},{"move":{"name":"night-slash"},"version_group_details":[{"level_learned_at":42,"move_learn_method":{"name":"level-up"}}]},{"move":{"name":"x-scissor"},"version_group_details":[{"move_learn_method":{"name":"machine"}}]},{"move":{"name":"bug-buzz"},"version_group_details":[{"level_learned_at":46,"move_learn_method":{"name":"level-up"}}]},{"move":{"name":"giga-impact"},"version_group_details":[{"move_learn_method":{"name":"machine"}}]},{"move":{"name":"captivate"},"version_group_details":[{"move_learn_method":{"name":"machine"}}]},{"move":{"name":"bug-bite"},"version_group_details":[{"level_learned_at":0,"move_learn_method":{"name":"level-up"}}]},{"move":{"name":"hone-claws"},"version_group_details":[{"move_learn_method":{"name":"machine"}}]},{"move":{"name":"round"},"version_group_details":[{"move_learn_method":{"name":"machine"}}]},{"move":{"name":"echoed-voice"},"version_group_details":[{"move_learn_method":{"name":"machine"}}]},{"move":{"name":"struggle-bug"},"version_group_details":[{"move_learn_method":{"name":"machine"}}]},{"move":{"name":"sticky-web"},"version_group_details":[{"level_learned_at":44,"move_learn_method":{"name":"level-up"}}]},{"move":{"name":"fell-stinger"},"version_group_details":[{"level_learned_at":36,"move_learn_method":{"name":"level-up"}}]},{"move":{"name":"confide"},"version_group_details":[{"move_learn_method":{"name":"machine"}}]},{"move":{"name":"infestation"},"version_group_details":[{"move_learn_method":{"name":"machine"}}]},{"move":{"name":"power-up-punch"},"version_group_details":[{"move_learn_method":{"name":"machine"}}]}],"name":"kricketune","species":{"base_happiness":70,"capture_rate":45,"egg_groups":[{"name":"bug"}],"flavor_text_entries":[{"flavor_text":"It crosses its knifelike arms in\nfront of its chest when it cries.\nIt can compose melodies ad lib.","language":{"name":"en"}}],"gender_rate":4,"genera":[{"genus":"Cricket Pokémon","language":{"name":"en"}}],"growth_rate":{"name":"Medium-Slow"},"hatch_counter":15,"id":402},"stats":[{"base_stat":77},{"base_stat":85},{"base_stat":51},{"base_stat":55},{"base_stat":51},{"base_stat":65}],"types":[{"slot":1,"type":{"name":"bug"}}],"weight":255}
