{"abilities":[{"ability":{"name":"schooling"},"is_hidden":false}],"base_experience":61,"height":2,"held_items":[],"moves":[{"move":{"name":"take-down"},"version_group_details":[{"level_learned_at":25,"move_learn_method":{"name":"level-up"}}]},{"move":{"name":"double-edge"},"version_group_details":[{"level_learned_at":41,"move_learn_method":{"name":"level-up"}}]},{"move":{"name":"growl"},"version_group_details":[{"level_learned_at":1,"move_learn_method":{"name":"level-up"}}]},{"move":{"name":"mist"},"version_group_details":[{"move_learn_method":{"name":"egg"}}]},{"move":{"name":"water-gun"},"version_group_details":[{"level_learned_at":1,"move_learn_method":{"name":"level-up"}}]},{"move":{"name":"hydro-pump"},"version_group_details":[{"level_learned_at":54,"move_learn_method":{"name":"level-up"}}]},{"move":{"name":"surf"},"version_group_details":[{"move_learn_method":{"name":"machine"}}]},{"move":{"name":"ice-beam"},"version_group_details":[{"move_learn_method":{"name":"machine"}}]},{"move":{"name":"earthquake"},"version_group_details":[{"move_learn_method":{"name":"machine"}}]},{"move":{"name":"toxic"},"version_group_details":[{"move_learn_method":{"name":"machine"}}]},{"move":{"name":"double-team"},"version_group_details":[{"move_learn_method":{"name":"machine"}}]},{"move":{"name":"waterfall"},"version_group_details":[{"move_learn_method":{"name":"machine"}}]},{"move":{"name":"rest"},"version_group_details":[{"move_learn_method":{"name":"machine"}}]},{"move":{"name":"substitute"},"version_group_details":[{"move_learn_method":{"name":"machine"}}]},{"move":{"name":"protect"},"version_group_details":[{"move_learn_method":{"name":"machine"}}]},{"move":{"name":"feint-attack"},"version_group_details":[{"level_learned_at":9,"move_learn_method":{"name":"level-up"}}]},{"move":{"name":"swagger"},"version_group_details":[{"move_learn_method":{"name":"machine"}}]},{"move":{"name":"attract"},"version_group_details":[{"move_learn_method":{"name":"machine"}}]},{"move":{"name":"sleep-talk"},"version_group_details":[{"move_learn_method":{"name":"machine"}}]},{"move":{"name":"return"},"version_group_details":[{"move_learn_method":{"name":"machine"}}]},{"move":{"name":"frustration"},"version_group_details":[{"move_learn_method":{"name":"machine"}}]},{"move":{"name":"hidden-power"},"version_group_details":[{"move_learn_method":{"name":"machine"}}]},{"move":{"name":"rain-dance"},"version_group_details":[{"move_learn_method":{"name":"machine"}}]},{"move":{"name":"whirlpool"},"version_group_details":[{"move_learn_method":{"name":"egg"}}]},{"move":{"name":"beat-up"},"version_group_details":[{"level_learned_at":33,"move_learn_method":{"name":"level-up"}}]},{"move":{"name":"hail"},"version_group_details":[{"move_learn_method":{"name":"machine"}}]},{"move":{"name":"facade"},"version_group_details":[{"move_learn_method":{"name":"machine"}}]},{"move":{"name":"helping-hand"},"version_group_details":[{"level_learned_at":6,"move_learn_method":{"name":"level-up"}}]},{"move":{"name":"endeavor"},"version_group_details":[{"level_learned_at":49,"move_learn_method":{"name":"level-up"}}]},{"move":{"name":"dive"},"version_group_details":[{"level_learned_at":30,"move_learn_method":{"name":"level-up"}}]},{"move":{"name":"muddy-water"},"version_group_details":[{"move_learn_method":{"name":"egg"}}]},{"move":{"name":"water-sport"},"version_group_details":[{"move_learn_method":{"name":"egg"}}]},{"move":{"name":"water-pulse"},"version_group_details":[{"move_learn_method":{"name":"egg"}}]},{"move":{"name":"brine"},"version_group_details":[{"level_learned_at":14,"move_learn_method":{"name":"level-up"}}]},{"move":{"name":"u-turn"},"version_group_details":[{"move_learn_method":{"name":"machine"}}]},{"move":{"name":"aqua-ring"},"version_group_details":[{"level_learned_at":17,"move_learn_method":{"name":"level-up"}}]},{"move":{"name":"aqua-tail"},"version_group_details":[{"level_learned_at":38,"move_learn_method":{"name":"level-up"}}]},{"move":{"name":"soak"},"version_group_details":[{"level_learned_at":46,"move_learn_method":{"name":"level-up"}}]},{"move":{"name":"round"},"version_group_details":[{"move_learn_method":{"name":"machine"}}]},{"move":{"name":"scald"},"version_group_details":[{"move_learn_method":{"name":"machine"}}]},{"move":{"name":"bulldoze"},"version_group_details":[{"move_learn_method":{"name":"machine"}}]},{"move":{"name":"confide"},"version_group_details":[{"move_learn_method":{"name":"machine"}}]},{"move":{"name":"tearful-look"},"version_group_details":[{"level_learned_at":22,"move_learn_method":{"name":"level-up"}}]}],"name":"wishiwashi-solo","species":{"base_happiness":70,"capture_rate":60,"egg_groups":[{"name":"water2"}],"flavor_text_entries":[{"flavor_text":"When it’s in trouble, its eyes moisten and begin\nto shine. The shining light attracts its comrades,\nand they stand together against their enemies.","language":{"name":"en"}}],"gender_rate":4,"genera":[{"genus":"Small Fry Pokémon","language":{"name":"en"}}],"growth_rate":{"name":"Fast"},"hatch_counter":15,"id":746},"stats":[{"base_stat":45},{"base_stat":20},{"base_stat":20},{"base_stat":25},{"base_stat":25},{"base_stat":40}],"types":[{"slot":1,"type":{"name":"water"}}],"weight":3}
